LICENSE.txt
MANIFEST.in
README.rst
requirements.txt
setup.cfg
setup.py
doc/Makefile
doc/conf.py
doc/htk.1
doc/index.rst
doc/objects.inv
doc/rst/install.rst
doc/rst/module.rst
doc/rst/refman.rst
doc/rst/tutor.rst
doc/rst/install/installing.rst
doc/rst/install/requirements.rst
doc/rst/module/extensions.rst
doc/rst/module/hydratk.rst
doc/rst/module/ext/benchmark/benchmark.rst
doc/rst/module/ext/benchmark/main.rst
doc/rst/module/ext/benchmark/tests.rst
doc/rst/module/hydra/core.rst
doc/rst/module/hydra/lib.rst
doc/rst/module/hydra/core/bootstrapper.rst
doc/rst/module/hydra/core/config.rst
doc/rst/module/hydra/core/corehead.rst
doc/rst/module/hydra/core/dbconfig.rst
doc/rst/module/hydra/core/debugger.rst
doc/rst/module/hydra/core/events.rst
doc/rst/module/hydra/core/extension.rst
doc/rst/module/hydra/core/hookhead.rst
doc/rst/module/hydra/core/logger.rst
doc/rst/module/hydra/core/masterhead.rst
doc/rst/module/hydra/core/messaging.rst
doc/rst/module/hydra/core/propertyhead.rst
doc/rst/module/hydra/core/servicehead.rst
doc/rst/module/hydra/core/template.rst
doc/rst/module/hydra/lib/array.rst
doc/rst/module/hydra/lib/compat.rst
doc/rst/module/hydra/lib/console.rst
doc/rst/module/hydra/lib/cycles.rst
doc/rst/module/hydra/lib/data.rst
doc/rst/module/hydra/lib/database.rst
doc/rst/module/hydra/lib/debugging.rst
doc/rst/module/hydra/lib/dynamic.rst
doc/rst/module/hydra/lib/exceptions.rst
doc/rst/module/hydra/lib/install.rst
doc/rst/module/hydra/lib/number.rst
doc/rst/module/hydra/lib/string.rst
doc/rst/module/hydra/lib/system.rst
doc/rst/module/hydra/lib/translation.rst
doc/rst/refman/ext/benchmark.rst
doc/rst/refman/hydra/core.rst
doc/rst/refman/hydra/lib.rst
doc/rst/tutor/extensions.rst
doc/rst/tutor/hydratk.rst
doc/rst/tutor/ext/benchmark/benchmark.rst
doc/rst/tutor/ext/benchmark/tut1_bench.rst
doc/rst/tutor/hydra/tut1_cli.rst
doc/rst/tutor/hydra/tut2_cfg.rst
doc/rst/tutor/hydra/tut3_lib.rst
doc/rst/tutor/hydra/tut4_ext.rst
etc/hydratk/hydratk.conf
src/hydratk/__init__.py
src/hydratk.egg-info/PKG-INFO
src/hydratk.egg-info/SOURCES.txt
src/hydratk.egg-info/dependency_links.txt
src/hydratk.egg-info/entry_points.txt
src/hydratk.egg-info/not-zip-safe
src/hydratk.egg-info/top_level.txt
